analyzequicker/__init__.py
analyzequicker/analyzequicker.py
analyzequicker-0.0.1.dist-info/METADATA
analyzequicker-0.0.1.dist-info/WHEEL
analyzequicker-0.0.1.dist-info/licenses/LICENSE
analyzequicker-0.0.1.dist-info/RECORD
